setup.py
src/pydiscovery/__init__.py
src/pydiscovery/finder.py
src/pydiscovery.egg-info/PKG-INFO
src/pydiscovery.egg-info/SOURCES.txt
src/pydiscovery.egg-info/dependency_links.txt
src/pydiscovery.egg-info/requires.txt
src/pydiscovery.egg-info/top_level.txt