Metadata-Version: 1.0
Name: pydiscovery
Version: 0.1
Summary: Network discovery
Home-page: UNKNOWN
Author: Christopher Probst
Author-email: christopher-probst@online.de
License: UNKNOWN
Platform: UNKNOWN
